context_compressor/__init__.py
context_compressor/compressor.py
context_compressor/summarizers.py
context_compressor/tokenizer.py
context_compressor/types.py
context_compressor_llm-0.1.2.dist-info/METADATA
context_compressor_llm-0.1.2.dist-info/WHEEL
context_compressor_llm-0.1.2.dist-info/top_level.txt
context_compressor_llm-0.1.2.dist-info/RECORD
