Metadata-Version: 2.4
Name: context-compressor-llm
Version: 0.1.2
Summary: Incremental context compression for LLMs with anchored summaries
Author-email: LaguePesikin <wagnlpesikin@gmail.com>
License: MIT
Project-URL: Homepage, https://github.com/LaguePesikin/context-compressor
Project-URL: Documentation, https://github.com/LaguePesikin/context-compressor
Project-URL: Repository, https://github.com/LaguePesikin/context-compressor
Keywords: llm,context,compression,ai,nlp
Classifier: Development Status :: 3 - Alpha
Classifier: Intended Audience :: Developers
Classifier: Topic :: Scientific/Engineering :: Artificial Intelligence
Classifier: License :: OSI Approved :: MIT License
Classifier: Programming Language :: Python :: 3
Classifier: Programming Language :: Python :: 3.8
Classifier: Programming Language :: Python :: 3.9
Classifier: Programming Language :: Python :: 3.10
Classifier: Programming Language :: Python :: 3.11
Classifier: Programming Language :: Python :: 3.12
Requires-Python: >=3.8
Requires-Dist: tiktoken>=0.5.0
Provides-Extra: dev
Requires-Dist: pytest>=7.0.0; extra == "dev"
Requires-Dist: pytest-cov>=4.0.0; extra == "dev"
Requires-Dist: black>=23.0.0; extra == "dev"
Requires-Dist: flake8>=6.0.0; extra == "dev"
Requires-Dist: mypy>=1.0.0; extra == "dev"
